{
  "collectionName": "components_fiche_solution_aide_regionales",
  "info": {
    "displayName": "aide_regionale",
    "description": ""
  },
  "options": {},
  "attributes": {
    "region": {
      "type": "relation",
      "relation": "oneToOne",
      "target": "api::region.region"
    },
    "description": {
      "type": "customField",
      "options": {
        "output": "HTML",
        "preset": "default"
      },
      "customField": "plugin::ckeditor5.CKEditor",
      "required": true
    },
    "titre": {
      "type": "string"
    }
  }
}
